hpa/__init__.py
hpa/base.py
hpa/hpa_discovery.py
tests/__init__.py
tests/test.py
tests/test_hpa_discovery.py
onaphpadriver-1.0.dist-info/LICENSE
onaphpadriver-1.0.dist-info/METADATA
onaphpadriver-1.0.dist-info/WHEEL
onaphpadriver-1.0.dist-info/entry_points.txt
onaphpadriver-1.0.dist-info/top_level.txt
onaphpadriver-1.0.dist-info/RECORD
